MANIFEST.in
README.md
requirements.txt
setup.cfg
setup.py
test-requirements.txt
txbalanced/__init__.py
txbalanced/config.py
txbalanced/exc.py
txbalanced/resources.py
txbalanced/utils.py
txbalanced.egg-info/PKG-INFO
txbalanced.egg-info/SOURCES.txt
txbalanced.egg-info/dependency_links.txt
txbalanced.egg-info/pbr.json
txbalanced.egg-info/requires.txt
txbalanced.egg-info/top_level.txt