Metadata-Version: 1.1
Name: txbalanced
Version: 0.1.1
Summary: Payments platform for marketplaces (twisted fork)
Home-page: https://github.com/trenton42/txbalanced
Author: Balanced
Author-email: dev@balancedpayments.com
License: BSD
Platform: UNKNOWN
Classifier: Intended Audience :: Developers
Classifier: License :: OSI Approved :: BSD License
Classifier: Programming Language :: Python
Classifier: Topic :: Software Development :: Libraries :: Python Modules
